xmpy_sqlite/__init__.py
xmpy_sqlite/sqlite_database.py
xmpy_sqlite-1.1.4.dist-info/METADATA
xmpy_sqlite-1.1.4.dist-info/WHEEL
xmpy_sqlite-1.1.4.dist-info/licenses/LICENSE
xmpy_sqlite-1.1.4.dist-info/RECORD
