Metadata-Version: 2.4
Name: xmpy_sqlite
Version: 1.1.4
Summary: xmpy框架的SQLite数据库接口
Project-URL: Homepage, https://github.com/InkAbyss/xmpy_sqlite
Project-URL: Issues, https://github.com/InkAbyss/xmpy_sqlite/issues
Author-email: bhzy <2024305928@qq.com>
License: MIT
License-File: LICENSE
Keywords: algotrading,investment,quant,quantitative,trading
Classifier: Development Status :: 5 - Production/Stable
Classifier: License :: OSI Approved :: MIT License
Classifier: Natural Language :: Chinese (Simplified)
Classifier: Operating System :: OS Independent
Classifier: Programming Language :: Python :: 3
Classifier: Programming Language :: Python :: 3.10
Classifier: Programming Language :: Python :: 3.11
Classifier: Programming Language :: Python :: 3.12
Classifier: Programming Language :: Python :: 3.13
Classifier: Programming Language :: Python :: Implementation :: CPython
Classifier: Topic :: Office/Business :: Financial :: Investment
Classifier: Typing :: Typed
Requires-Python: >=3.10
Requires-Dist: peewee>=3.17.9
